quotesfromthematrix/__init__.py
quotesfromthematrix-1.0.6.dist-info/METADATA
quotesfromthematrix-1.0.6.dist-info/WHEEL
quotesfromthematrix-1.0.6.dist-info/top_level.txt
quotesfromthematrix-1.0.6.dist-info/RECORD
