Metadata-Version: 2.2
Name: quotesfromthematrix
Version: 1.0.6
Summary: A library that quotes Morpheus from The Matrix.
Author: Regina
Requires-Python: >=3.6
Dynamic: author
Dynamic: description
Dynamic: description-content-type
Dynamic: requires-python
Dynamic: summary
